LICENSE
MANIFEST.in
README.md
requisites.txt
roundcube_merge_databases.py
setup.py
roundcube_merge_databases.egg-info/PKG-INFO
roundcube_merge_databases.egg-info/SOURCES.txt
roundcube_merge_databases.egg-info/dependency_links.txt
roundcube_merge_databases.egg-info/entry_points.txt
roundcube_merge_databases.egg-info/not-zip-safe
roundcube_merge_databases.egg-info/requires.txt
roundcube_merge_databases.egg-info/top_level.txt