Metadata-Version: 1.0
Name: roundcube-merge-databases
Version: 0.1.5
Summary: Merge roundcube users/identities/contacts from one database into another handling id's
Home-page: https://github.com/nitidum/roundcube_merge_databases.git
Author: Jordi Llonch
Author-email: llonchj@gmail.com
License: UNKNOWN
Platform: UNKNOWN
